setup.py
docs/INSTALL.txt
docs/LICENSE.GPL
docs/LICENSE.txt
plonehrm/__init__.py
plonehrm.notes.egg-info/PKG-INFO
plonehrm.notes.egg-info/SOURCES.txt
plonehrm.notes.egg-info/dependency_links.txt
plonehrm.notes.egg-info/entry_points.txt
plonehrm.notes.egg-info/namespace_packages.txt
plonehrm.notes.egg-info/not-zip-safe
plonehrm.notes.egg-info/requires.txt
plonehrm.notes.egg-info/top_level.txt
plonehrm/notes/HISTORY.txt
plonehrm/notes/README.txt
plonehrm/notes/__init__.py
plonehrm/notes/configure.zcml
plonehrm/notes/interfaces.py
plonehrm/notes/notes.py
plonehrm/notes/permissions.zcml
plonehrm/notes/rebuild_i18n.sh
plonehrm/notes/version.txt
plonehrm/notes/browser/__init__.py
plonehrm/notes/browser/configure.zcml
plonehrm/notes/browser/notes.kss
plonehrm/notes/browser/notes.pt
plonehrm/notes/browser/notes.py
plonehrm/notes/browser/notes_listing.pt
plonehrm/notes/locales/notes.pot
plonehrm/notes/locales/en/LC_MESSAGES/notes.po
plonehrm/notes/locales/nl/LC_MESSAGES/notes.po
plonehrm/notes/locales/pt_BR/LC_MESSSAGES/notes.po
plonehrm/notes/profiles/default/kssregistry.xml
plonehrm/notes/profiles/default/rolemap.xml
plonehrm/notes/tests/__init__.py
plonehrm/notes/tests/base.py
plonehrm/notes/tests/browser.txt
plonehrm/notes/tests/test_integration.py
plonehrm/notes/tests/test_unit.py