Metadata-Version: 1.0
Name: plonehrm.notes
Version: 1.0.7
Summary: A plonehrm extension module to add notes to an employee.
Home-page: http://svn.plone.org/svn/collective/plonehrm.notes
Author: Jean-Paul Ladage
Author-email: j.ladage@zestsoftware.nl
License: GPL
Keywords: hrm notes
Platform: UNKNOWN
Classifier: Framework :: Plone
Classifier: Framework :: Zope2
Classifier: Framework :: Zope3
Classifier: Programming Language :: Python
Classifier: Topic :: Software Development :: Libraries :: Python Modules
